ipyradiant/__init__.py
ipyradiant/_version.py
ipyradiant/basic_tools/__init__.py
ipyradiant/basic_tools/custom_uri_ref.py
ipyradiant/basic_tools/object_literal_collapsing.py
ipyradiant/basic_tools/selection_widget.py
ipyradiant/basic_tools/uri_widgets.py
ipyradiant/loader/__init__.py
ipyradiant/loader/base.py
ipyradiant/loader/manager.py
ipyradiant/loader/path.py
ipyradiant/loader/upload.py
ipyradiant/loader/util.py
ipyradiant/query/__init__.py
ipyradiant/query/app.py
ipyradiant/query/framer.py
ipyradiant/query/utils.py
ipyradiant/query/visualize.py
ipyradiant/rdf2nx/__init__.py
ipyradiant/rdf2nx/converter.py
ipyradiant/rdf2nx/edges.py
ipyradiant/rdf2nx/literal_converter.py
ipyradiant/rdf2nx/nodes.py
ipyradiant/rdf2nx/uri_converter.py
ipyradiant/tests/__init__.py
ipyradiant/tests/conftest.py
ipyradiant/tests/test_CustomURI.py
ipyradiant/tests/test_PredCollapsing.py
ipyradiant/tests/test_framer.py
ipyradiant/tests/test_queries.py
ipyradiant/tests/test_rdf2nx.py
ipyradiant/tests/test_servicepatch_rdflib.py
ipyradiant/visualization/__init__.py
ipyradiant/visualization/base.py
ipyradiant/visualization/datashader_vis.py
ipyradiant/visualization/tools.py
ipyradiant/visualization/cytoscape/__init__.py
ipyradiant/visualization/cytoscape/app.py
ipyradiant/visualization/cytoscape/interactive.py
ipyradiant/visualization/cytoscape/style.py
ipyradiant/visualization/cytoscape/utils.py
ipyradiant/visualization/cytoscape/viewer.py
ipyradiant-0.2.0.dist-info/LICENSE
ipyradiant-0.2.0.dist-info/METADATA
ipyradiant-0.2.0.dist-info/WHEEL
ipyradiant-0.2.0.dist-info/top_level.txt
ipyradiant-0.2.0.dist-info/RECORD
