Metadata-Version: 2.1
Name: ipyradiant
Version: 0.2.0
Summary: Jupyter Widgets for working with RDF graphs
Home-page: https://github.com/jupyrdf/ipyradiant
Author: ipyradiant Contributors
Author-email: welz.zachary@gmail.com
License: BSD-3-Clause
Keywords: Interactive,Language Server,LSP,RDF
Platform: UNKNOWN
Classifier: Framework :: Jupyter
Classifier: Intended Audience :: Developers
Classifier: Intended Audience :: Information Technology
Classifier: License :: OSI Approved :: BSD License
Classifier: Programming Language :: Python
Requires-Python: >=3.6
Requires-Dist: bokeh
Requires-Dist: datashader
Requires-Dist: holoviews
Requires-Dist: ipycytoscape (>=1.2)
Requires-Dist: ipywidgets (<8,>=7.6)
Requires-Dist: networkx (>=2)
Requires-Dist: pandas
Requires-Dist: rdflib
Requires-Dist: rdflib-jsonld
Requires-Dist: scikit-image
Provides-Extra: lab3
Requires-Dist: jupyterlab (==3.*) ; extra == 'lab3'
Requires-Dist: ipycytoscape (>=1.2.0) ; extra == 'lab3'
Requires-Dist: pyviz-comms (>=1.0.3) ; extra == 'lab3'
